pyimpBB/__init__.py
pyimpBB/analyzing.py
pyimpBB/bounding.py
pyimpBB/helper.py
pyimpBB/solver.py
pyimpbb-0.2.1.dist-info/licenses/LICENSE.txt
pyimpbb-0.2.1.dist-info/METADATA
pyimpbb-0.2.1.dist-info/WHEEL
pyimpbb-0.2.1.dist-info/top_level.txt
pyimpbb-0.2.1.dist-info/RECORD
