Metadata-Version: 2.4
Name: pyimpBB
Version: 0.2.1
Summary: Implementation of an algorithm from the field of global optimization according to the publication ‘The improvement function in branch-and-bound methods for complete global optimization’ by S. Schwarze, O. Stein, P. Kirst and M. Rodestock.
Author: Marc Rodestock
Author-email: marc@fam-rodestock.de
License: MIT
Project-URL: Institution, https://www.ior.kit.edu
Project-URL: Source, https://github.com/uisab/pyimpBB
Keywords: global optimization,improvement function,branch-and-bound method
Classifier: Development Status :: 4 - Beta
Classifier: License :: OSI Approved :: MIT License
Classifier: Programming Language :: Python :: 3.9
Classifier: Operating System :: OS Independent
License-File: LICENSE.txt
Requires-Dist: numpy
Requires-Dist: matplotlib
Requires-Dist: pyinterval
Requires-Dist: scipy
Dynamic: author
Dynamic: author-email
Dynamic: classifier
Dynamic: description
Dynamic: description-content-type
Dynamic: keywords
Dynamic: license
Dynamic: license-file
Dynamic: project-url
Dynamic: requires-dist
Dynamic: summary
